docs/logo2.webp
docs/logo3.webp
docs/img/ratingRGNN.svg
torch_rating/__init__.py
torch_rating/_rating_layers/__init__.py
torch_rating/_rating_layers/_berrar.py
torch_rating/_rating_layers/_elo.py
torch_rating/_rating_layers/_general_rating.py
torch_rating/_rating_layers/_pi.py
torch_rating-0.0.2.dist-info/LICENSE
torch_rating-0.0.2.dist-info/METADATA
torch_rating-0.0.2.dist-info/WHEEL
torch_rating-0.0.2.dist-info/top_level.txt
torch_rating-0.0.2.dist-info/RECORD
