Metadata-Version: 2.1
Name: torch-rating
Version: 0.0.2
Summary: Seamless integration of sports rating systems as layers into pytorch environment
Author-email: Jakub Sukdol <sukdojak@fel.cvut.cz>
License: MIT License
Project-URL: repository, https://github.com/kubosis/torch-rating
Keywords: GNN,Sport prediction,Rating
Classifier: Development Status :: 4 - Beta
Classifier: Programming Language :: Python
Requires-Python: >=3.10
License-File: LICENSE
Requires-Dist: torch>=2.1.2
Requires-Dist: numpy>=1.24.4
